llm_tools_exa.py
llm_tools_exa-0.5.0.dist-info/licenses/LICENSE
llm_tools_exa-0.5.0.dist-info/METADATA
llm_tools_exa-0.5.0.dist-info/WHEEL
llm_tools_exa-0.5.0.dist-info/entry_points.txt
llm_tools_exa-0.5.0.dist-info/top_level.txt
llm_tools_exa-0.5.0.dist-info/RECORD
