Metadata-Version: 2.4
Name: llm-tools-exa
Version: 0.5.0
Summary: A tool plugin for LLM to enable web search with Exa
Author-email: Dan Turkel <daturkel@gmail.com>
License-Expression: MIT
Requires-Python: >=3.9
License-File: LICENSE
Requires-Dist: exa-py>=2.0.0
Requires-Dist: llm>=0.26
Provides-Extra: test
Requires-Dist: pytest>=8.3.5; extra == "test"
Dynamic: license-file
